nonebot_plugin_zxui/__init__.py
nonebot_plugin_zxui/config.py
nonebot_plugin_zxui/models/ban_console.py
nonebot_plugin_zxui/models/bot_connect_log.py
nonebot_plugin_zxui/models/bot_console.py
nonebot_plugin_zxui/models/chat_history.py
nonebot_plugin_zxui/models/fg_request.py
nonebot_plugin_zxui/models/group_console.py
nonebot_plugin_zxui/models/level_user.py
nonebot_plugin_zxui/models/plugin_info.py
nonebot_plugin_zxui/models/plugin_limit.py
nonebot_plugin_zxui/models/statistics.py
nonebot_plugin_zxui/stat/__init__.py
nonebot_plugin_zxui/stat/chat_history/__init__.py
nonebot_plugin_zxui/stat/chat_history/chat_message.py
nonebot_plugin_zxui/stat/record_request.py
nonebot_plugin_zxui/stat/statistics/__init__.py
nonebot_plugin_zxui/stat/statistics/statistics_hook.py
nonebot_plugin_zxui/web_ui/__init__.py
nonebot_plugin_zxui/web_ui/api/__init__.py
nonebot_plugin_zxui/web_ui/api/logs/__init__.py
nonebot_plugin_zxui/web_ui/api/logs/log_manager.py
nonebot_plugin_zxui/web_ui/api/logs/logs.py
nonebot_plugin_zxui/web_ui/api/menu/__init__.py
nonebot_plugin_zxui/web_ui/api/menu/data_source.py
nonebot_plugin_zxui/web_ui/api/menu/model.py
nonebot_plugin_zxui/web_ui/api/tabs/__init__.py
nonebot_plugin_zxui/web_ui/api/tabs/dashboard/__init__.py
nonebot_plugin_zxui/web_ui/api/tabs/dashboard/data_source.py
nonebot_plugin_zxui/web_ui/api/tabs/dashboard/model.py
nonebot_plugin_zxui/web_ui/api/tabs/database/__init__.py
nonebot_plugin_zxui/web_ui/api/tabs/database/data_source.py
nonebot_plugin_zxui/web_ui/api/tabs/database/models/model.py
nonebot_plugin_zxui/web_ui/api/tabs/database/models/sql_log.py
nonebot_plugin_zxui/web_ui/api/tabs/main/__init__.py
nonebot_plugin_zxui/web_ui/api/tabs/main/data_source.py
nonebot_plugin_zxui/web_ui/api/tabs/main/model.py
nonebot_plugin_zxui/web_ui/api/tabs/manage/__init__.py
nonebot_plugin_zxui/web_ui/api/tabs/manage/chat.py
nonebot_plugin_zxui/web_ui/api/tabs/manage/data_source.py
nonebot_plugin_zxui/web_ui/api/tabs/manage/model.py
nonebot_plugin_zxui-0.3.7.dist-info/LICENSE
nonebot_plugin_zxui-0.3.7.dist-info/METADATA
nonebot_plugin_zxui-0.3.7.dist-info/WHEEL
nonebot_plugin_zxui-0.3.7.dist-info/RECORD
