Metadata-Version: 2.1
Name: nonebot-plugin-zxui
Version: 0.3.7
Summary: 
Author: HibiKier
Author-email: 775757368@qq.com
Requires-Python: >=3.10,<4.0
Classifier: Programming Language :: Python :: 3
Classifier: Programming Language :: Python :: 3.10
Classifier: Programming Language :: Python :: 3.11
Classifier: Programming Language :: Python :: 3.12
Requires-Dist: fastapi (>=0.115.6,<0.116.0)
Requires-Dist: nonebot-plugin-alconna (>=0.54.1,<0.55.0)
Requires-Dist: nonebot-plugin-apscheduler (>=0.5.0,<0.6.0)
Requires-Dist: nonebot-plugin-localstore (>=0.7.3,<0.8.0)
Requires-Dist: nonebot-plugin-session (>=0.3.2,<0.4.0)
Requires-Dist: nonebot-plugin-uninfo (>=0.6.2,<0.7.0)
Requires-Dist: nonebot2 (>=2.3.3,<3.0.0)
Requires-Dist: psutil (>=6.1.1,<7.0.0)
Requires-Dist: python-jose (>=3.3.0,<4.0.0)
Requires-Dist: python-multipart (>=0.0.20,<0.0.21)
Requires-Dist: ruamel-yaml (>=0.18.6,<0.19.0)
Requires-Dist: ujson (>=5.10.0,<6.0.0)
Requires-Dist: websockets (>=14.1,<15.0)
Requires-Dist: zhenxun-db-client (>=0.1.2,<0.2.0)
Requires-Dist: zhenxun-utils (>=0.2.2,<0.3.0)
